Metadata-Version: 2.1
Name: pyASCIIgenerator
Version: 1.0.0
Summary: A simple image-to-ASCII converter based on a video by Kite
Home-page: https://github.com/HYKANTUS/pyASCIIgenerator
Author: HYKANTUS
Author-email: hykantus@gmail.com
License: UNKNOWN
Project-URL: Personal Website, http://hykantus.tk/
Project-URL: Source, https://github.com/HYKANTUS/pyASCIIgenerator/
Keywords: ASCII,image,ASCIIart,ASCII art,ASCIIimage,ASCII image,image,art,fun,Pillow,PIL,PIL Image
Platform: UNKNOWN
Classifier: Development Status :: 5 - Production/Stable
Classifier: Intended Audience :: Developers
Classifier: Topic :: Software Development :: Build Tools
Classifier: License :: OSI Approved :: MIT License
Classifier: Programming Language :: Python :: 3
Classifier: Programming Language :: Python :: 3.6
Classifier: Programming Language :: Python :: 3.7
Classifier: Programming Language :: Python :: 3.8
Classifier: Programming Language :: Python :: 3.9
Classifier: Programming Language :: Python :: 3 :: Only
Requires-Python: >=3.6, <4
